[
    {
        "nid": "Surge",
        "name": "Surge",
        "desc": "Cannot miss.",
        "icon_nid": "items",
        "icon_index": [
            2,
            1
        ],
        "components": [
            [
                "weapon",
                null
            ],
            [
                "value",
                560
            ],
            [
                "target_enemy",
                null
            ],
            [
                "min_range",
                1
            ],
            [
                "max_range",
                1
            ],
            [
                "damage",
                8
            ],
            [
                "crit",
                0
            ],
            [
                "weight",
                5
            ],
            [
                "uses",
                40
            ],
            [
                "uses_options",
                [
                    [
                        "LoseUsesOnMiss (T/F)",
                        "F",
                        "Lose uses even on miss"
                    ]
                ]
            ],
            [
                "level_exp",
                null
            ],
            [
                "weapon_type",
                "Magic"
            ],
            [
                "weapon_rank",
                "D"
            ],
            [
                "map_hit_add_blend",
                [
                    85,
                    170,
                    255
                ]
            ],
            [
                "magic",
                null
            ]
        ]
    }
]