[
    {
        "nid": "HighKhat",
        "name": "High (Khat)",
        "desc": "This unit is high on Khat.",
        "icon_nid": "ZessDynamiteSkillsysSuneohair",
        "icon_index": [
            4,
            80
        ],
        "components": [
            [
                "time",
                2
            ],
            [
                "stat_change",
                [
                    [
                        "STR",
                        8
                    ],
                    [
                        "SPD",
                        8
                    ]
                ]
            ]
        ]
    }
]